dbl_boundary_service/__init__.py
dbl_boundary_service/boundary_flow.py
dbl_boundary_service/config.py
dbl_boundary_service/llm_adapter.py
dbl_boundary_service/main.py
dbl_boundary_service/pipeline_factory.py
dbl_boundary_service/security.py
dbl_boundary_service/telemetry.py
dbl_boundary_service/web/__init__.py
dbl_boundary_service/web/ui.py
dbl_boundary_service-0.2.1.dist-info/licenses/LICENSE
dbl_boundary_service-0.2.1.dist-info/METADATA
dbl_boundary_service-0.2.1.dist-info/WHEEL
dbl_boundary_service-0.2.1.dist-info/entry_points.txt
dbl_boundary_service-0.2.1.dist-info/top_level.txt
dbl_boundary_service-0.2.1.dist-info/RECORD
