Metadata-Version: 2.4
Name: dbl-boundary-service
Version: 0.2.1
Summary: Reference service exposing a governed LLM boundary via DBL and KL
Author: Lukas Pfister
License: MIT
Keywords: dbl,kl,llm,governance,boundary,deterministic
Classifier: Development Status :: 2 - Pre-Alpha
Classifier: Intended Audience :: Developers
Classifier: License :: OSI Approved :: MIT License
Classifier: Programming Language :: Python :: 3.11
Classifier: Programming Language :: Python :: 3.12
Classifier: Typing :: Typed
Requires-Python: >=3.11
License-File: LICENSE
Requires-Dist: fastapi>=0.115.0
Requires-Dist: uvicorn>=0.30.0
Requires-Dist: httpx>=0.28.1
Requires-Dist: dbl-main>=0.3.0
Requires-Dist: dbl-core>=0.3.0
Requires-Dist: dbl-policy>=0.1.0
Requires-Dist: kl-kernel-logic==0.5.0
Provides-Extra: dev
Requires-Dist: pytest>=8.0.0; extra == "dev"
Dynamic: license-file
